final_project_shiyinglai/__init__.py
final_project_shiyinglai/final_project_shiyinglai.py
final_project_shiyinglai-2.8.0.dist-info/LICENSE
final_project_shiyinglai-2.8.0.dist-info/WHEEL
final_project_shiyinglai-2.8.0.dist-info/METADATA
final_project_shiyinglai-2.8.0.dist-info/RECORD
